pygating/__init__.py
pygating/gates/__init__.py
pygating/gates/and_gate.py
pygating/gates/boolean_gate.py
pygating/gates/comparison_gate.py
pygating/gates/custom_script_gate.py
pygating/gates/date_comparison_gate.py
pygating/gates/date_gate.py
pygating/gates/inclusion_gate.py
pygating/gates/list_container_gate.py
pygating/gates/numeric_comparison_gate.py
pygating/gates/or_gate.py
pygating/gates/percentage_gate.py
pygating/gates/property_gating_type.py
pygating/gates/random_gate.py
pygating/gates/regex_gate.py
pygating/gates/simple_gate.py
pygating/gating_configurations/__init__.py
pygating/gating_configurations/gating_configuration_all.py
pygating/gating_configurations/gating_configuration_any.py
pygating/pygating.py
pygating-1.0.6.dist-info/LICENSE
pygating-1.0.6.dist-info/METADATA
pygating-1.0.6.dist-info/WHEEL
pygating-1.0.6.dist-info/RECORD
