Metadata-Version: 2.1
Name: pygating
Version: 1.0.6
Summary: A small package for creating and using configurations to control code flow
Home-page: https://github.com/atsaplin/pygating
Author: Aleksey Tsaplin
Author-email: tsapleksey@gmail.com
Requires-Python: >=3.7
Classifier: Programming Language :: Python :: 3
Classifier: Programming Language :: Python :: 3.7
Classifier: Programming Language :: Python :: 3.8
Classifier: Programming Language :: Python :: 3.9
Classifier: Programming Language :: Python :: 3.10
Classifier: Programming Language :: Python :: 3.11
Classifier: Programming Language :: Python :: 3.12
Classifier: Programming Language :: Python :: 3.13
Requires-Dist: pytest
Requires-Dist: pytest-mock
Requires-Dist: python-dateutil
Project-URL: Documentation, https://github.com/atsaplin/pygating
Project-URL: Repository, https://github.com/atsaplin/pygating
